{"cameraMode":{"drawMode":0,"name":"Shaded","section":"Shading Mode"},"sceneLighting":false,"audioPlay":false,"sceneViewState":{"m_AlwaysRefresh":false,"showFog":true,"showSkybox":false,"showFlares":true,"showImageEffects":true,"showParticleSystems":true,"showVisualEffectGraphs":true,"m_FxEnabled":true},"in2DMode":false,"pivot":{"x":-3.550649404525757,"y":0.9930880069732666,"z":-21.0876522064209},"rotation":{"x":-0.22505399584770204,"y":0.6656712293624878,"z":-0.2215578705072403,"w":-0.676136314868927},"size":0.639207661151886,"orthographic":false}